flask_frame/__init__.py
flask_frame/app.py
flask_frame/permission_context.py
flask_frame/algorithm/__init__.py
flask_frame/algorithm/text.py
flask_frame/annotation/__init__.py
flask_frame/api/__init__.py
flask_frame/api/exception.py
flask_frame/api/request.py
flask_frame/api/response.py
flask_frame/extension/__init__.py
flask_frame/extension/celery.py
flask_frame/extension/consul.py
flask_frame/extension/lock.py
flask_frame/extension/marshmallow.py
flask_frame/extension/minio.py
flask_frame/extension/permission.py
flask_frame/extension/redis.py
flask_frame/extension/sentry.py
flask_frame/extension/api_log/__init__.py
flask_frame/extension/api_log/model.py
flask_frame/extension/database/__init__.py
flask_frame/extension/database/model.py
flask_frame/extension/loguru/__init__.py
flask_frame/extension/loguru/compress.py
flask_frame/extension/loguru/macro.py
flask_frame/extension/postgrest/__init__.py
flask_frame/extension/postgrest/sql_generator.py
flask_frame/extension/postgrest/util.py
flask_frame/schema/__init__.py
flask_frame/thread/__init__.py
flask_frame/thread/dk_thread_pool.py
flask_frame/thread/my_synchronized.py
flask_frame/util/__init__.py
flask_frame/util/com_tool.py
flask_frame/util/db.py
flask_frame/util/enum.py
flask_frame/util/fernet_tool.py
flask_frame/util/file.py
flask_frame/util/json.py
flask_frame/util/lock.py
flask_frame/util/model.py
flask_frame/util/param_tool.py
flask_frame/util/py_utils.py
flask_frame/util/rsa_tool.py
flask_frame/util/sql_tool.py
flask_frame-1.1.35.dist-info/licenses/LICENSE
flask_frame-1.1.35.dist-info/METADATA
flask_frame-1.1.35.dist-info/WHEEL
flask_frame-1.1.35.dist-info/top_level.txt
flask_frame-1.1.35.dist-info/RECORD
