Metadata-Version: 2.4
Name: flask_frame
Version: 1.1.35
Summary: 基于FLASK快速开发REST接口框架
Author: wuhanchu
Author-email: whcwuhanchu@gmail.com
License-File: LICENSE
Requires-Dist: Flask==3.1.0
Requires-Dist: flask_marshmallow==1.3.0
Requires-Dist: marshmallow==3.26.1
Requires-Dist: marshmallow-sqlalchemy==1.4.2
Requires-Dist: celery==5.5.1
Requires-Dist: pyinstrument==5.0.1
Requires-Dist: sentry_sdk==2.26.1
Requires-Dist: Requests==2.32.3
Requires-Dist: redis==5.2.1
Requires-Dist: Flask_SQLAlchemy==3.1.1
Requires-Dist: SQLAlchemy==2.0.40
Requires-Dist: psycopg2-binary==2.9.10
Requires-Dist: rsa==4.9
Requires-Dist: gunicorn==23.0.0
Requires-Dist: gevent==24.11.1
Requires-Dist: tenacity==9.1.2
Requires-Dist: loguru==0.7.3
Requires-Dist: pytz~=2025.2
Requires-Dist: python-consul2==0.1.5
Requires-Dist: minio==7.2.9
Requires-Dist: cryptography==46.0.1
Dynamic: author
Dynamic: author-email
Dynamic: license-file
Dynamic: requires-dist
Dynamic: summary
